confused_argparse/__init__.py
confused_argparse/py.typed
confused_argparse-0.2.2.dist-info/LICENSE
confused_argparse-0.2.2.dist-info/WHEEL
confused_argparse-0.2.2.dist-info/METADATA
confused_argparse-0.2.2.dist-info/RECORD
