Metadata-Version: 2.1
Name: confused-argparse
Version: 0.2.2
Summary: 'My standard' goto package for all my scripts/apps. Get argparse cli and configuration management in ONE LINE per parameter ;-)
Home-page: https://github.com/cruisen/confused-argparse
License: MIT
Requires-Python: >=3.6,<4.0
Classifier: Development Status :: 3 - Alpha
Classifier: Intended Audience :: Developers
Classifier: License :: OSI Approved :: MIT License
Classifier: Operating System :: OS Independent
Classifier: Programming Language :: Python :: 3
Classifier: Programming Language :: Python :: 3.6
Classifier: Programming Language :: Python :: 3.7
Classifier: Programming Language :: Python :: 3.8
Classifier: Topic :: Software Development :: Libraries :: Python Modules
Project-URL: Repository, https://github.com/cruisen/confused-argparse
